README.md
keyfinder.cpp
setup.py
keyfinder/__init__.py
keyfinder/notations.py
keyfinder.egg-info/PKG-INFO
keyfinder.egg-info/SOURCES.txt
keyfinder.egg-info/dependency_links.txt
keyfinder.egg-info/top_level.txt