Metadata-Version: 2.1
Name: keyfinder
Version: 1.1.0
Summary: Determine the key of an audio file
Home-page: https://github.com/evanpurkhiser/keyfinder-py
Author: Evan Purkhiser
Author-email: evanpurkhiser@gmail.com
License: UNKNOWN
Platform: UNKNOWN
Classifier: Topic :: Multimedia :: Sound/Audio
Classifier: Topic :: Multimedia :: Sound/Audio :: Analysis
